flask_socket_generator_app/__init__.py
flask_socket_generator_app/main.py
flask_socket_generator_app/project_builder.py
flask_socket_generator_app/project_manager.py
flask_socket_generator_app/versions.py
templates/__init__.py
templates/docker_compose.py
templates/docker_file.py
templates/gitignore.py
templates/index_html.py
templates/main.py
templates/readme.py
templates/requirements_txt.py
flask_socketio_generator-1.0.1.dist-info/METADATA
flask_socketio_generator-1.0.1.dist-info/WHEEL
flask_socketio_generator-1.0.1.dist-info/entry_points.txt
flask_socketio_generator-1.0.1.dist-info/top_level.txt
flask_socketio_generator-1.0.1.dist-info/RECORD
