Metadata-Version: 2.2
Name: flask_socketio_generator
Version: 1.0.1
Summary: The lib generates the template for Flask app with SoketIO configuration.
Author-email: Serhiy Bezrukaviy <sergey.bezrukavyy@gmail.com>
